mytestpkgone/__init__.py
mytestpkgone-0.0.1.dist-info/Licence.txt
mytestpkgone-0.0.1.dist-info/METADATA
mytestpkgone-0.0.1.dist-info/WHEEL
mytestpkgone-0.0.1.dist-info/top_level.txt
mytestpkgone-0.0.1.dist-info/RECORD
